epubhv-0.6.0.dist-info/METADATA
epubhv-0.6.0.dist-info/WHEEL
epubhv-0.6.0.dist-info/entry_points.txt
epubhv-0.6.0.dist-info/licenses/LICENSE
epubhv/__init__.py
epubhv/__main__.py
epubhv/cli.py
epubhv/epubhv.py
epubhv/punctuation.py
epubhv/yomituki.py
epubhv-0.6.0.dist-info/RECORD
