Metadata-Version: 2.1
Name: epubhv
Version: 0.6.0
Summary: make your epub books vertical or horizontal.
Author-Email: yihong0618 <zouzou0208@gmail.com>
License: MIT
Project-URL: Homepage, https://github.com/yihong0618/epubhv
Requires-Python: !=3.9.7,>=3.8
Requires-Dist: beautifulsoup4==4.12.2
Requires-Dist: cssutils==2.7.1
Requires-Dist: lxml==4.9.3
Requires-Dist: opencc-python-reimplemented==0.1.7
Requires-Dist: soupsieve==2.5
Requires-Dist: typed-argument-parser==1.8.1
Requires-Dist: jieba
Requires-Dist: pypinyin
Requires-Dist: unidic_lite
Requires-Dist: fugashi
Requires-Dist: langdetect
Requires-Dist: ToJyutping
Requires-Dist: streamlit>=1.29.0; extra == "web"
Provides-Extra: web
